[{"date":"Bugün","team1":"Ç. Rizespor","team2":"Denizlispor"},{"date":"Cuma","team1":"Göztepe","team2":"Bandırmaspor"},{"date":"28.01","team1":"Tuzlaspor","team2":"Sakaryaspor"},{"date":"28.01","team1":"Altınordu","team2":"Boluspor"},{"date":"28.01","team1":"Pendikspor","team2":"Gençlerbirliği"},{"date":"29.01","team1":"Adanaspor","team2":"Bodrumspor"},{"date":"29.01","team1":"Keçiörengücü","team2":"Altay"},{"date":"29.01","team1":"Yeni Malatya","team2":"Eyüpspor"},{"date":"29.01","team1":"Denizlispor","team2":"Manisa FK"}]