[{"date":"Yarın","team1":"Bandırmaspor","team2":"Boluspor"},{"date":"Yarın","team1":"Ümraniyespor","team2":"Ankaragücü"},{"date":"Yarın","team1":"Gençlerbirliği","team2":"Keçiörengücü"},{"date":"Yarın","team1":"Adanaspor","team2":"Balıkesirspor"},{"date":"10.04","team1":"Manisa FK","team2":"Samsunspor"},{"date":"10.04","team1":"Denizlispor","team2":"Tuzlaspor"},{"date":"10.04","team1":"Menemenspor","team2":"İstanbulspor"},{"date":"10.04","team1":"Bursaspor","team2":"Kocaelispor"},{"date":"11.04","team1":"Eyüpspor","team2":"Altınordu"}]