[{"date":"12:00","team1":"Kırşehir Bld.","team2":"Karacabey Bld."},{"date":"12:30","team1":"Sivas Bld.","team2":"Bodrumspor"},{"date":"14:00","team1":"Turgutluspor","team2":"1922 Konyaspor"},{"date":"14:00","team1":"Serik Belediye","team2":"Tarsus İY"},{"date":"14:00","team1":"Pendikspor","team2":"Pazarspor"},{"date":"14:00","team1":"Mamak FK","team2":"Sakaryaspor"},{"date":"14:00","team1":"Karabükspor","team2":"Eyüpspor"},{"date":"14:00","team1":"Etimesgut Bld.","team2":"Kastamonuspor"},{"date":"14:00","team1":"Elazığspor","team2":"Vanspor FK"},{"date":"14:00","team1":"Bayburt İÖİ","team2":"Kırklarelispor"}]