[{"date":"Bugün","team1":"Başkent Gözgözler","team2":"Hendekspor"},{"date":"Yarın","team1":"1954 Kelkit Bld.","team2":"Sancaktepe FK"},{"date":"Yarın","team1":"Artvin Hopa","team2":"Elazığspor"},{"date":"Yarın","team1":"Bergama Bld.","team2":"Batman Petrol"},{"date":"Yarın","team1":"Bursa Yıldırımspor","team2":"Arnavutköy Bld."},{"date":"Yarın","team1":"Çatalcaspor","team2":"Erbaaspor"},{"date":"Yarın","team1":"Fatsa Belediye","team2":"Bld. Kütahyaspor"},{"date":"Yarın","team1":"Karaman Bld.","team2":"Kahta 02 SK"},{"date":"Yarın","team1":"Osmaniyespor","team2":"Nevşehir Bld."}]