[{"date":"11.02","team1":"Çatalcaspor","team2":"Elazığspor"},{"date":"Bugün","team1":"1954 Kelkit Bld.","team2":"Şile Yıldızspor"},{"date":"Bugün","team1":"52 Orduspor","team2":"Bld. Kütahyaspor"},{"date":"Bugün","team1":"Ağrı 1970 SK","team2":"Nevşehir Bld."},{"date":"Bugün","team1":"Amasyaspor FK","team2":"Bld. Derincespor"},{"date":"Bugün","team1":"Eskişehirspor","team2":"Karaköprü Bld."},{"date":"Bugün","team1":"Karşıyaka","team2":"Hacettepe 1945 SK"},{"date":"Bugün","team1":"Yeni Mersin İY","team2":"Edirnespor"},{"date":"Bugün","team1":"Yomraspor","team2":"1922 Konyaspor"}]