[{"date":"Bugün","team1":"B. Tepecikspor","team2":"Niğde Anadolu FK"},{"date":"12.04","team1":"Çankaya FK","team2":"Arguvanspor"},{"date":"12.04","team1":"Sapanca Gençlik","team2":"Osmaniyespor"},{"date":"Çar.","team1":"68 Aksaray Belediye","team2":"Kepez Belediye"},{"date":"Çar.","team1":"Artvin Hopa","team2":"Muş 1984 Muşspor"},{"date":"Çar.","team1":"Bergama Belediye","team2":"Bursa Yıldırımspor"},{"date":"Çar.","team1":"Beyoğlu Yeni Çarşı","team2":"Efeler 09"},{"date":"Çar.","team1":"Fatsa Belediye","team2":"B. Tepecikspor"},{"date":"Çar.","team1":"Niğde Anadolu FK","team2":"Akhisarspor"}]