[{"date":"14.08","team1":"Adanaspor","team2":"Tuzlaspor","score1":"v"},{"date":"14.08","team1":"Altay","team2":"Samsunspor","score1":"v"},{"date":"14.08","team1":"BB Erzurumspor","team2":"Pendikspor","score1":"v"},{"date":"14.08","team1":"Bodrumspor","team2":"Yeni Malatya","score1":"v"},{"date":"14.08","team1":"Ç. Rizespor","team2":"Keçiörengücü","score1":"v"},{"date":"14.08","team1":"Eyüpspor","team2":"Denizlispor","score1":"v"},{"date":"14.08","team1":"Gençlerbirliği","team2":"Altınordu","score1":"v"},{"date":"14.08","team1":"Manisa FK","team2":"Boluspor","score1":"v"},{"date":"14.08","team1":"Sakaryaspor","team2":"Göztepe","score1":"v"}]