[{"date":"Yarın","team1":"Göztepe","team2":"Boluspor","score1":"20 00"},{"date":"Yarın","team1":"Pendikspor","team2":"Altınordu","score1":"20 00"},{"date":"Cts.","team1":"Keçiörengücü","team2":"Bandırmaspor","score1":"13 30"},{"date":"Cts.","team1":"Tuzlaspor","team2":"Gençlerbirliği","score1":"13 30"},{"date":"Cts.","team1":"Adanaspor","team2":"Eyüpspor","score1":"16 00"},{"date":"Cts.","team1":"Samsunspor","team2":"Ç. Rizespor","score1":"19 00"},{"date":"Pazar","team1":"Bodrumspor","team2":"Altay","score1":"13 30"},{"date":"Pazar","team1":"Yeni Malatya","team2":"Manisa FK","score1":"16 00"},{"date":"Pazar","team1":"Denizlispor","team2":"Sakaryaspor","score1":"19 00"}]