[{"date":"14.01 13:00","team1":"Bayburt İÖİ","team2":"Sakaryaspor","score1":"2","score2":"4"},{"date":"10.01 13:00","team1":"Kırklarelispor","team2":"Bayburt İÖİ","score1":"3","score2":"2"},{"date":"10.01 13:00","team1":"Pazarspor","team2":"Pendikspor","score1":"1","score2":"1"},{"date":"10.01 13:00","team1":"Tarsus İY","team2":"Kastamonuspor","score1":"2","score2":"0"},{"date":"06.01 13:00","team1":"Bodrumspor","team2":"Turgutluspor","score1":"4","score2":"1"},{"date":"06.01 13:00","team1":"Karacabey Bld.","team2":"Etimesgut Bld.","score1":"1","score2":"1"},{"date":"06.01 13:00","team1":"Kırklarelispor","team2":"Tarsus İY","score1":"1","score2":"1"},{"date":"06.01 13:00","team1":"Kırşehir Bld.","team2":"Karabükspor","score1":"4","score2":"0"},{"date":"06.01 13:00","team1":"Mamak FK","team2":"Serik Belediye","score1":"2","score2":"1"},{"date":"06.01 13:00","team1":"Pazarspor","team2":"1922 Konyaspor","score1":"2","score2":"0"}]