[{"date":"Yarın","team1":"Ankara Demir","team2":"Pazarspor","score1":"15 00"},{"date":"Yarın","team1":"Etimesgut Bld.","team2":"1461 Trabzon FK","score1":"15 00"},{"date":"Yarın","team1":"Kastamonuspor","team2":"Fethiyespor","score1":"15 00"},{"date":"Yarın","team1":"Kırşehir FK","team2":"Uşakspor","score1":"15 00"},{"date":"Yarın","team1":"Serik Belediye","team2":"Bucaspor 1928","score1":"15 00"},{"date":"Yarın","team1":"Kocaelispor","team2":"Balıkesirspor","score1":"15 30"},{"date":"Yarın","team1":"Sarıyer","team2":"Kırklarelispor","score1":"15 30"},{"date":"Yarın","team1":"Karacabey Bld.","team2":"Adıyaman FK","score1":"16 00"},{"date":"Yarın","team1":"Diyarbekirspor","team2":"Zonguldak Kömür","score1":"19 00"},{"date":"Yarın","team1":"İskenderun FK","team2":"Vanspor FK","score1":"19 00"}]