[{"date":"Yarın","team1":"Arnavutköy Bld.","team2":"Osmaniyespor","score1":"14 00"},{"date":"Yarın","team1":"Batman Petrol","team2":"1954 Kelkit Bld.","score1":"14 00"},{"date":"Yarın","team1":"Bld. Kütahyaspor","team2":"Karaman Bld.","score1":"14 00"},{"date":"Yarın","team1":"Bursa Yıldırımspor","team2":"Artvin Hopa","score1":"14 00"},{"date":"Yarın","team1":"Elazığspor","team2":"Sancaktepe FK","score1":"14 00"},{"date":"Yarın","team1":"Erbaaspor","team2":"Bergama Bld.","score1":"14 00"},{"date":"Yarın","team1":"Fatsa Belediye","team2":"Başkent Gözgözler","score1":"14 00"},{"date":"Yarın","team1":"Hendekspor","team2":"Çatalcaspor","score1":"14 00"},{"date":"Yarın","team1":"Nevşehir Bld.","team2":"Kahta 02 SK","score1":"14 00"}]