[{"date":"Yarın","team1":"Arguvanspor","team2":"Osmaniyespor","score1":"v"},{"date":"Yarın","team1":"68 Aksaray Belediye","team2":"Çankaya FK","score1":"14 00"},{"date":"Yarın","team1":"Akhisarspor","team2":"Sapanca Gençlik","score1":"14 00"},{"date":"Yarın","team1":"Artvin Hopa","team2":"Bergama Belediye","score1":"14 00"},{"date":"Yarın","team1":"Kepez Belediye","team2":"Siirt İl Özel İdare","score1":"14 00"},{"date":"Yarın","team1":"Muş 1984 Muşspor","team2":"Erbaaspor","score1":"14 00"},{"date":"19.03","team1":"Osmaniyespor","team2":"Bursa Yıldırımspor","score1":"v"},{"date":"19.03","team1":"Sapanca Gençlik","team2":"Arguvanspor","score1":"v"},{"date":"19.03","team1":"Bergama Belediye","team2":"Kepez Belediye","score1":"14 00"}]