{"tableTitle":"1. Lig Puan Durumu","columns":["S","Takım","O","G","B","M","A","Y","Av","P"],"list":[{"S":"1","Takım":"Eyüpspor","O":"6","G":"4","B":"1","M":"1","A":"10","Y":"7","Av":"3","P":"13"},{"S":"2","Takım":"Bodrumspor","O":"6","G":"3","B":"2","M":"1","A":"13","Y":"8","Av":"5","P":"11"},{"S":"3","Takım":"Keçiörengücü","O":"6","G":"3","B":"2","M":"1","A":"12","Y":"10","Av":"2","P":"11"},{"S":"4","Takım":"Boluspor","O":"5","G":"3","B":"1","M":"1","A":"5","Y":"3","Av":"2","P":"10"},{"S":"5","Takım":"Bandırmaspor","O":"5","G":"3","B":"1","M":"1","A":"8","Y":"7","Av":"1","P":"10"},{"S":"6","Takım":"Sakaryaspor","O":"6","G":"3","B":"0","M":"3","A":"9","Y":"7","Av":"2","P":"9"},{"S":"7","Takım":"Samsunspor","O":"6","G":"2","B":"3","M":"1","A":"9","Y":"7","Av":"2","P":"9"},{"S":"8","Takım":"Pendikspor","O":"6","G":"2","B":"3","M":"1","A":"5","Y":"4","Av":"1","P":"9"},{"S":"9","Takım":"Manisa FK","O":"5","G":"2","B":"2","M":"1","A":"7","Y":"6","Av":"1","P":"8"},{"S":"10","Takım":"Tuzlaspor","O":"6","G":"2","B":"2","M":"2","A":"8","Y":"8","Av":"0","P":"8"},{"S":"11","Takım":"Göztepe","O":"6","G":"2","B":"2","M":"2","A":"4","Y":"4","Av":"0","P":"8"},{"S":"12","Takım":"Adanaspor","O":"6","G":"1","B":"4","M":"1","A":"8","Y":"7","Av":"1","P":"7"},{"S":"13","Takım":"Ç. Rizespor","O":"5","G":"1","B":"3","M":"1","A":"6","Y":"4","Av":"2","P":"6"},{"S":"14","Takım":"Gençlerbirliği","O":"6","G":"1","B":"3","M":"2","A":"9","Y":"10","Av":"-1","P":"6"},{"S":"15","Takım":"Altay","O":"6","G":"1","B":"2","M":"3","A":"4","Y":"7","Av":"-3","P":"5"},{"S":"16","Takım":"Altınordu","O":"5","G":"0","B":"3","M":"2","A":"5","Y":"8","Av":"-3","P":"3"},{"S":"17","Takım":"Erzurumspor FK","O":"5","G":"0","B":"3","M":"2","A":"6","Y":"10","Av":"-4","P":"3"},{"S":"18","Takım":"Yeni Malatya","O":"6","G":"0","B":"3","M":"3","A":"6","Y":"13","Av":"-7","P":"3"},{"S":"19","Takım":"Denizlispor","O":"6","G":"0","B":"2","M":"4","A":"5","Y":"9","Av":"-4","P":"2"}]}