{"tableTitle":"2. Lig Kırmızı Grup Puan Durumu","columns":["S","Takım","O","G","B","M","A","Y","Av","P"],"list":[{"S":"1","Takım":"Eyüpspor","O":"18","G":"14","B":"2","M":"2","A":"43","Y":"14","Av":"29","P":"44"},{"S":"2","Takım":"Vanspor FK","O":"18","G":"11","B":"4","M":"3","A":"30","Y":"16","Av":"14","P":"37"},{"S":"3","Takım":"Turgutluspor","O":"18","G":"12","B":"0","M":"6","A":"22","Y":"25","Av":"-3","P":"36"},{"S":"4","Takım":"Sakaryaspor","O":"16","G":"9","B":"4","M":"3","A":"26","Y":"15","Av":"11","P":"31"},{"S":"5","Takım":"Kırşehir Bld.","O":"18","G":"8","B":"6","M":"4","A":"23","Y":"15","Av":"8","P":"30"},{"S":"6","Takım":"Serik Belediye","O":"17","G":"7","B":"7","M":"3","A":"27","Y":"19","Av":"8","P":"28"},{"S":"7","Takım":"Bodrumspor","O":"18","G":"7","B":"5","M":"6","A":"40","Y":"29","Av":"11","P":"26"},{"S":"8","Takım":"Sivas Bld.","O":"18","G":"6","B":"8","M":"4","A":"31","Y":"22","Av":"9","P":"26"},{"S":"9","Takım":"Kırklarelispor","O":"17","G":"6","B":"8","M":"3","A":"19","Y":"12","Av":"7","P":"26"},{"S":"10","Takım":"Pazarspor","O":"16","G":"8","B":"2","M":"6","A":"27","Y":"24","Av":"3","P":"26"},{"S":"11","Takım":"Karacabey Bld.","O":"18","G":"7","B":"4","M":"7","A":"22","Y":"19","Av":"3","P":"25"},{"S":"12","Takım":"Tarsus İY","O":"17","G":"6","B":"5","M":"6","A":"25","Y":"19","Av":"6","P":"23"},{"S":"13","Takım":"Etimesgut Bld.","O":"18","G":"6","B":"5","M":"7","A":"17","Y":"19","Av":"-2","P":"23"},{"S":"14","Takım":"1922 Konyaspor","O":"18","G":"5","B":"4","M":"9","A":"22","Y":"20","Av":"2","P":"19"},{"S":"15","Takım":"Pendikspor","O":"17","G":"5","B":"1","M":"11","A":"23","Y":"24","Av":"-1","P":"16"},{"S":"16","Takım":"Kastamonuspor","O":"17","G":"4","B":"4","M":"9","A":"16","Y":"26","Av":"-10","P":"16"},{"S":"17","Takım":"Mamak FK","O":"17","G":"4","B":"4","M":"9","A":"18","Y":"41","Av":"-23","P":"16"},{"S":"18","Takım":"Elazığspor","O":"18","G":"5","B":"3","M":"10","A":"24","Y":"35","Av":"-11","P":"15"},{"S":"19","Takım":"Bayburt İÖİ","O":"16","G":"4","B":"2","M":"10","A":"11","Y":"25","Av":"-14","P":"14"},{"S":"20","Takım":"Karabükspor","O":"18","G":"0","B":"2","M":"16","A":"6","Y":"53","Av":"-47","P":"-1"}]}