{"tableTitle":"3. Lig 1. Grup Puan Durumu","columns":["S","Takım","O","G","B","M","A","Y","Av","P"],"list":[{"S":"1","Takım":"Diyarbekirspor","O":"13","G":"10","B":"2","M":"1","A":"19","Y":"7","Av":"12","P":"32"},{"S":"2","Takım":"Bucaspor 1928","O":"13","G":"9","B":"2","M":"2","A":"26","Y":"9","Av":"17","P":"29"},{"S":"3","Takım":"Ofspor","O":"13","G":"6","B":"4","M":"3","A":"21","Y":"16","Av":"5","P":"22"},{"S":"4","Takım":"Edirnespor","O":"13","G":"6","B":"3","M":"4","A":"19","Y":"16","Av":"3","P":"21"},{"S":"5","Takım":"Fatsa Belediye","O":"13","G":"6","B":"3","M":"4","A":"12","Y":"12","Av":"0","P":"21"},{"S":"6","Takım":"M. Yeşilyurt Bld.","O":"13","G":"6","B":"2","M":"5","A":"20","Y":"11","Av":"9","P":"20"},{"S":"7","Takım":"Bld. Derincespor","O":"13","G":"5","B":"5","M":"3","A":"17","Y":"11","Av":"6","P":"20"},{"S":"8","Takım":"Arnavutköy Bld.","O":"12","G":"5","B":"3","M":"4","A":"12","Y":"11","Av":"1","P":"18"},{"S":"9","Takım":"Artvin Hopa","O":"13","G":"5","B":"1","M":"7","A":"19","Y":"28","Av":"-9","P":"16"},{"S":"10","Takım":"Nevşehir Bld.","O":"13","G":"4","B":"3","M":"6","A":"13","Y":"14","Av":"-1","P":"15"},{"S":"11","Takım":"1877 Alemdağspor","O":"13","G":"4","B":"3","M":"6","A":"17","Y":"23","Av":"-6","P":"15"},{"S":"12","Takım":"Kızılcabölükspor","O":"13","G":"3","B":"4","M":"6","A":"16","Y":"21","Av":"-5","P":"13"},{"S":"13","Takım":"Çankaya FK","O":"12","G":"4","B":"1","M":"7","A":"9","Y":"16","Av":"-7","P":"13"},{"S":"14","Takım":"Payasspor","O":"13","G":"3","B":"3","M":"7","A":"16","Y":"20","Av":"-4","P":"12"},{"S":"15","Takım":"Kemerspor","O":"13","G":"2","B":"4","M":"7","A":"13","Y":"23","Av":"-10","P":"10"},{"S":"16","Takım":"Manisaspor","O":"13","G":"1","B":"5","M":"7","A":"9","Y":"20","Av":"-11","P":"8"}]}